pyvlm/__init__.py
pyvlm/__main__.py
pyvlm/classes/__init__.py
pyvlm/classes/latticecontrol.py
pyvlm/classes/latticegrid.py
pyvlm/classes/latticeoptimum.py
pyvlm/classes/latticepanel.py
pyvlm/classes/latticeresult.py
pyvlm/classes/latticesection.py
pyvlm/classes/latticesheet.py
pyvlm/classes/latticestrip.py
pyvlm/classes/latticesurface.py
pyvlm/classes/latticesystem.py
pyvlm/classes/latticetrim.py
pyvlm/outputs/__init__.py
pyvlm/outputs/md.py
pyvlm/outputs/msh.py
pyvlm/outputs/prf.py
pyvlm/tools/__init__.py
pyvlm/tools/airfoil.py
pyvlm/tools/bell.py
pyvlm/tools/camber.py
pyvlm/tools/cupy.py
pyvlm/tools/elliptical.py
pyvlm/tools/mass.py
pyvlm/tools/numpy.py
pyvlm/tools/stability.py
pyvlm/tools/trim.py
pyvlm-0.0.12.dist-info/licenses/LICENSE
pyvlm-0.0.12.dist-info/METADATA
pyvlm-0.0.12.dist-info/WHEEL
pyvlm-0.0.12.dist-info/entry_points.txt
pyvlm-0.0.12.dist-info/top_level.txt
pyvlm-0.0.12.dist-info/RECORD
