Metadata-Version: 2.4
Name: pyvlm
Version: 0.0.12
Summary: Vortex Lattice Method in Python
Author-email: Xero64 <xero64@gmail.com>
License-Expression: MIT
Project-URL: Homepage, https://github.com/Xero64/pyvlm
Project-URL: Issues, https://github.com/Xero64/pyvlm/issues
Classifier: Programming Language :: Python :: 3
Classifier: Operating System :: OS Independent
Requires-Python: >=3.10
License-File: LICENSE
Requires-Dist: matplotlib>=3.10.5
Requires-Dist: numexpr>=2.11.0
Requires-Dist: py2md>=0.1.3
Requires-Dist: pygeom>=0.0.14
Dynamic: license-file
